FastHttpServer/__init__.py
FastHttpServer-0.0.1.dist-info/LICENSE
FastHttpServer-0.0.1.dist-info/METADATA
FastHttpServer-0.0.1.dist-info/WHEEL
FastHttpServer-0.0.1.dist-info/top_level.txt
FastHttpServer-0.0.1.dist-info/RECORD
