Metadata-Version: 2.1
Name: FastHttpServer
Version: 0.0.1
Summary: An extremely lightweight and fast http server
Home-page: https://github.com/D4r3d3vil/FastHttp
Author: Mulham Alamry
Author-email: mulhamreacts@gmail.com
License: MIT
Requires-Python: >=3.0
License-File: LICENSE
